valknut/__init__.py
valknut/valknut.py
valknut-0.0.2.data/scripts/valknut.py
valknut-0.0.2.dist-info/LICENSE
valknut-0.0.2.dist-info/METADATA
valknut-0.0.2.dist-info/WHEEL
valknut-0.0.2.dist-info/top_level.txt
valknut-0.0.2.dist-info/RECORD
