Metadata-Version: 2.1
Name: valknut
Version: 0.0.2
Summary: markdown to GSS converter, SQLite3 management system and Micro WSGI Server
Home-page: https://github.com/daniel67-py/Valknut_Project
Author: Meyer Daniel
Author-email: meyer.daniel67@protonmail.com
License: UNKNOWN
Platform: UNKNOWN
Classifier: Programming Language :: Python :: 3
Classifier: License :: OSI Approved :: MIT License
Classifier: Operating System :: OS Independent
Requires-Python: >=3.6
